django_payload_validator
