Metadata-Version: 1.1
Name: django-payload-validator
Version: 1.0.1
Summary: validator for django payload
Home-page: https://github.com/gladsonvm/django_payload_validator
Author: Gladson V Manuel
Author-email: gladsonvm@gmail.com
License: MIT
Keywords: django payload validator intended audience is dev
Platform: UNKNOWN
Classifier: Development Status :: 3 - Alpha
Classifier: Topic :: Software Development :: Libraries :: Application Frameworks
Classifier: Intended Audience :: Developers
Classifier: License :: OSI Approved :: MIT License
Classifier: Framework :: Django
Classifier: Programming Language :: Python :: 2
Classifier: Programming Language :: Python :: 2.7
Classifier: Programming Language :: Python :: 3
Classifier: Programming Language :: Python :: 3.4
Classifier: Programming Language :: Python :: 3.5
Classifier: Programming Language :: Python :: 3.6
